Metadata-Version: 2.1
Name: django-performance-monitor
Version: 1.0.0
Summary: A simple django applications to log the response time greater than a threshold value
Home-page: https://github.com/afsal-parseltongue/django-performance-monitor
Author: Afsal Salim
Author-email: afsal@parseltongue.co.in
License: UNKNOWN
Platform: UNKNOWN
Classifier: Environment :: Web Environment
Classifier: Framework :: Django
Classifier: Intended Audience :: Developers
Classifier: Operating System :: OS Independent
Classifier: Programming Language :: Python
Classifier: Programming Language :: Python :: 3.6
Classifier: Programming Language :: Python :: 3.7
Classifier: Programming Language :: Python :: 3.8
Classifier: Programming Language :: Python :: 3.9
Classifier: Programming Language :: Python :: 3.10
Classifier: License :: OSI Approved :: MIT License
Requires-Python: >=3.6
License-File: LICENSE
